openride/__init__.py
openride-0.0.2.dist-info/METADATA
openride-0.0.2.dist-info/WHEEL
openride-0.0.2.dist-info/top_level.txt
openride-0.0.2.dist-info/RECORD
