Metadata-Version: 2.1
Name: openride
Version: 0.0.2
Summary: UNKNOWN
Home-page: https://gitlab.com/jldez/openride
Author: Jean-Luc Déziel
Author-email: jluc1011@hotmail.com
License: UNKNOWN
Platform: UNKNOWN
Requires-Dist: dataclasses
Requires-Dist: matplotlib
Requires-Dist: numba
Requires-Dist: numpy
Requires-Dist: shapely
Requires-Dist: vtk
